odoo/addons/mrp_bom_attribute_match_duplicate_kit/README.rst
odoo/addons/mrp_bom_attribute_match_duplicate_kit/__init__.py
odoo/addons/mrp_bom_attribute_match_duplicate_kit/__manifest__.py
odoo/addons/mrp_bom_attribute_match_duplicate_kit/demo/res_users_demo.xml
odoo/addons/mrp_bom_attribute_match_duplicate_kit/i18n/es.po
odoo/addons/mrp_bom_attribute_match_duplicate_kit/i18n/it.po
odoo/addons/mrp_bom_attribute_match_duplicate_kit/i18n/mrp_bom_attribute_match_duplicate_kit.pot
odoo/addons/mrp_bom_attribute_match_duplicate_kit/models/__init__.py
odoo/addons/mrp_bom_attribute_match_duplicate_kit/models/product_template.py
odoo/addons/mrp_bom_attribute_match_duplicate_kit/readme/CONTEXT.rst
odoo/addons/mrp_bom_attribute_match_duplicate_kit/readme/CONTRIBUTORS.rst
odoo/addons/mrp_bom_attribute_match_duplicate_kit/readme/DESCRIPTION.rst
odoo/addons/mrp_bom_attribute_match_duplicate_kit/readme/HISTORY.rst
odoo/addons/mrp_bom_attribute_match_duplicate_kit/readme/USAGE.rst
odoo/addons/mrp_bom_attribute_match_duplicate_kit/security/ir.model.access.csv
odoo/addons/mrp_bom_attribute_match_duplicate_kit/security/security.xml
odoo/addons/mrp_bom_attribute_match_duplicate_kit/static/description/icon.png
odoo/addons/mrp_bom_attribute_match_duplicate_kit/static/description/index.html
odoo/addons/mrp_bom_attribute_match_duplicate_kit/tests/__init__.py
odoo/addons/mrp_bom_attribute_match_duplicate_kit/tests/common.py
odoo/addons/mrp_bom_attribute_match_duplicate_kit/tests/test_product_template.py
odoo/addons/mrp_bom_attribute_match_duplicate_kit/tests/test_product_template_kit_wizard.py
odoo/addons/mrp_bom_attribute_match_duplicate_kit/views/product_template_views.xml
odoo/addons/mrp_bom_attribute_match_duplicate_kit/wizard/__init__.py
odoo/addons/mrp_bom_attribute_match_duplicate_kit/wizard/product_template_kit_wizard.py
odoo/addons/mrp_bom_attribute_match_duplicate_kit/wizard/product_template_kit_wizard.xml
odoo14_addon_mrp_bom_attribute_match_duplicate_kit-14.0.1.1.1.dist-info/METADATA
odoo14_addon_mrp_bom_attribute_match_duplicate_kit-14.0.1.1.1.dist-info/WHEEL
odoo14_addon_mrp_bom_attribute_match_duplicate_kit-14.0.1.1.1.dist-info/top_level.txt
odoo14_addon_mrp_bom_attribute_match_duplicate_kit-14.0.1.1.1.dist-info/RECORD
